Workbook

Sheet Price Breakdown
A1: O-YES Integrated EMIS — Price breakdown by package (ETB)
A2: Blue numbers are editable inputs; totals, discounts and payment schedule update automatically.
A4: Component | B4: Package 1 Complete Platform (Web + mobile) | C4: Package 2 Complete Web (Web, all modules) | D4: Package 3 Core Operations (Web, 3 modules)
A5: Foundation (shared by every module)
A6: Discovery, requirements & UI/UX design | B6: 35000 | C6: 28000 | D6: 18000
A7: Core platform: database, API, sign-in, users & roles, audit log | B7: 55000 | C7: 45000 | D7: 38000
A8: Master Data & Settings | B8: 20000 | C8: 20000 | D8: 12000
A9: Workflow, approvals, alerts & notifications | B9: 35000 | C9: 32000 | D9: 16000
A10: Executive dashboard & reports | B10: 40000 | C10: 40000 | D10: 16000
A11: Business modules (web)
A12: Projects & MEAL | B12: 50000 | C12: 50000 | D12: 50000
A13: Finance & Grants | B13: 50000 | C13: 50000 | D13: 50000
A14: Procurement & Assets | B14: 40000 | C14: 40000 | D14: 40000
A15: Beneficiary & Accountability | B15: 35000 | C15: 35000 | D15: 0
A16: Human Capital (HRIS) | B16: 30000 | C16: 30000 | D16: 0
A17: Governance, Risk & Compliance | B17: 28000 | C17: 28000 | D17: 0
A18: Partnerships | B18: 12000 | C18: 12000 | D18: 0
A19: Mobile
A20: Offline-first Android app, sync service & field workflows | B20: 120000 | C20: 0 | D20: 0
A21: Delivery
A22: Excel data migration | B22: 15000 | C22: 15000 | D22: 8000
A23: Testing, deployment, training & handover | B23: 35000 | C23: 25000 | D23: 12000
A24: Subtotal (sum of components) | B24: =SUM(B5:B23) | C24: =SUM(C5:C23) | D24: =SUM(D5:D23)
A25: Discount (enter as a positive amount) | B25: 0 | C25: 0 | D25: 0
A26: TOTAL PACKAGE PRICE | B26: =B24-B25 | C26: =C24-C25 | D26: =D24-D25
A27: Share of Package 1 price | B27: =IF($B$26=0,0,B26/$B$26) | C27: =IF($B$26=0,0,C26/$B$26) | D27: =IF($B$26=0,0,D26/$B$26)
A28: Estimated delivery time (weeks) | B28: 24 | C28: 18 | D28: 12

Sheet Payment Schedule
A1: Payment milestones (ETB)
A2: Edit the blue percentages; they must add up to 100%.
A4: Milestone | B4: Share | C4: Package 1 | D4: Package 2 | E4: Package 3
A5: Contract signing | B5: 0.3 | C5: =$B5*'Price Breakdown'!B26 | D5: =$B5*'Price Breakdown'!C26 | E5: =$B5*'Price Breakdown'!D26
A6: Design & clickable prototype approved | B6: 0.3 | C6: =$B6*'Price Breakdown'!B26 | D6: =$B6*'Price Breakdown'!C26 | E6: =$B6*'Price Breakdown'!D26
A7: User acceptance testing passed | B7: 0.3 | C7: =$B7*'Price Breakdown'!B26 | D7: =$B7*'Price Breakdown'!C26 | E7: =$B7*'Price Breakdown'!D26
A8: Go-live & training complete | B8: 0.1 | C8: =$B8*'Price Breakdown'!B26 | D8: =$B8*'Price Breakdown'!C26 | E8: =$B8*'Price Breakdown'!D26
A9: Total | B9: =SUM(B5:B8) | C9: =SUM(C5:C8) | D9: =SUM(D5:D8) | E9: =SUM(E5:E8)
A10: =IF(ROUND(B9,4)=1,"","Warning: shares do not add up to 100%")

Sheet Upgrade Path
A1: Upgrade path — amounts paid are credited in full
A3: Step | B3: Pay now (ETB) | C3: Cumulative (ETB)
A4: Start with Package 3 — Core Operations | B4: ='Price Breakdown'!D26 | C4: =B4
A5: Upgrade to Package 2 — Complete Web | B5: ='Price Breakdown'!C26-'Price Breakdown'!D26 | C5: =C4+B5
A6: Upgrade to Package 1 — add mobile app | B6: ='Price Breakdown'!B26-'Price Breakdown'!C26 | C6: =C5+B6
A7: Or: Package 2 directly → add mobile later | B7: ='Price Breakdown'!B26-'Price Breakdown'!C26 | C7: ='Price Breakdown'!B26

Sheet Terms & Assumptions
A1: Terms & assumptions
A3: 1. All prices are in Ethiopian Birr (ETB). VAT treatment as stated in the final contract.
A4: 2. Included in every package: deployment, data migration for included modules, role-based training, user guide, 3 months free support.
A5: 3. Not included: hosting, domain and SMS fees (paid by O-YES directly), devices, new features outside the agreed scope, external accounting-software integration.
A6: 4. Optional annual support & maintenance after the free period: about 10% of the package price per year.
A7: 5. Upgrade prices (see Upgrade Path) are held for 12 months from go-live of the first package.
A8: 6. Prices valid for 60 days from the date of the proposal.
A9: 7. Timelines start once requirements are confirmed and assume timely feedback, sample data and a named O-YES contact.
